fy.py
test/__init__.py
test/test.py
words/__init__.py
words/words.txt
fy-1.6.0.dist-info/LICENSE
fy-1.6.0.dist-info/METADATA
fy-1.6.0.dist-info/WHEEL
fy-1.6.0.dist-info/entry_points.txt
fy-1.6.0.dist-info/top_level.txt
fy-1.6.0.dist-info/RECORD
