Metadata-Version: 2.1
Name: fy
Version: 1.6.0
Summary: Translate words via command line
Home-page: https://github.com/chenjiandongx/fy
Author: chenjiandongx
Author-email: chenjiandongx@qq.com
License: MIT
Platform: UNKNOWN
Classifier: Development Status :: 4 - Beta
Classifier: Environment :: Console
Classifier: Intended Audience :: Developers
Classifier: License :: OSI Approved :: MIT License
Classifier: Operating System :: OS Independent
Classifier: Programming Language :: Python :: 3.5
Classifier: Programming Language :: Python :: 3.6
Classifier: Programming Language :: Python :: 3.7
Classifier: Topic :: Software Development :: Libraries
Requires-Dist: requests
Requires-Dist: huepy
Requires-Dist: xmltodict
Requires-Dist: litecli
Requires-Dist: pony
Requires-Dist: googletrans
Requires-Dist: pangu
Requires-Dist: pywin32 ; sys_platform == "win32"
